README.md
setup.py
XMagics/Xsms.py
XMagics/__init__.py
XMagics.egg-info/PKG-INFO
XMagics.egg-info/SOURCES.txt
XMagics.egg-info/dependency_links.txt
XMagics.egg-info/requires.txt
XMagics.egg-info/top_level.txt