Metadata-Version: 2.1
Name: XMagics
Version: 1.0.4
Summary: XOne_Team library
Home-page: UNKNOWN
Author: Amr Elmenyawy
Author-email: xone.conect@gmail.com
License: UNKNOWN
Keywords: Best library
Platform: UNKNOWN
Classifier: Development Status :: 1 - Planning
Classifier: Intended Audience :: Developers
Classifier: Programming Language :: Python :: 3
Classifier: Operating System :: Unix
Classifier: Operating System :: MacOS :: MacOS X
Classifier: Operating System :: Microsoft :: Windows
